diseq/__init__.py
diseq/diseq.py
diseq-1.0.5.dist-info/METADATA
diseq-1.0.5.dist-info/WHEEL
diseq-1.0.5.dist-info/top_level.txt
diseq-1.0.5.dist-info/RECORD
